README.md
setup.cfg
setup.py
bin/ropt.py
bin/roviz.py
randopt/__init__.py
randopt/_version.py
randopt/command.py
randopt/samplers.py
randopt/statistics.py
randopt/utils.py
randopt.egg-info/PKG-INFO
randopt.egg-info/SOURCES.txt
randopt.egg-info/dependency_links.txt
randopt.egg-info/top_level.txt
randopt/experiment/__init__.py
randopt/experiment/evolutionary.py
randopt/experiment/experiment.py
randopt/experiment/grid_search.py
randopt/experiment/hyperband.py
randopt/objectives/__init__.py
randopt/objectives/objectives.py