Metadata-Version: 2.1
Name: randopt
Version: 0.2.6
Summary: Streamlined machine learning experiment management.
Home-page: https://github.com/seba-1511/randopt
Author: Seb Arnold
Author-email: smr.arnold@gmail.com
License: License :: OSI Approved :: Apache Software License
Download-URL: https://github.com/seba-1511/randopt/archive/0.2.6.zip
Platform: UNKNOWN
